season_detector/__init__.py
season_detector/app.py
season_detector/static/script.js
season_detector/static/styles.css
season_detector/templates/index.html
season_detector-0.1.0.dist-info/METADATA
season_detector-0.1.0.dist-info/WHEEL
season_detector-0.1.0.dist-info/entry_points.txt
season_detector-0.1.0.dist-info/top_level.txt
season_detector-0.1.0.dist-info/RECORD
