Metadata-Version: 2.1
Name: season-detector
Version: 0.1.0
Summary: A web app to detect the season based on an image's RGB values.
Home-page: https://github.com/S0UEI/season_detector
Author: soei
Author-email: s2222004@stu.musashino-u.ac.jp
Classifier: Programming Language :: Python :: 3
Classifier: License :: OSI Approved :: MIT License
Classifier: Operating System :: OS Independent
Requires-Python: >=3.6
Requires-Dist: Flask
Requires-Dist: Pillow
Requires-Dist: numpy
